runrun/__init__.py
runrun/builtin_command.py
runrun/command_parser.py
runrun/exceptions.py
runrun/models.py
runrun/runner.py
runrun-0.0.1.dist-info/METADATA
runrun-0.0.1.dist-info/WHEEL
runrun-0.0.1.dist-info/licenses/LICENSE
runrun-0.0.1.dist-info/RECORD
