Metadata-Version: 2.1
Name: runrun
Version: 0.0.1
Summary: A typed command line parser
Project-URL: Source, https://github.com/Apollo-Roboto/python-runrun
Author-email: Apollo Roboto <apollo_roboto@outlook.com>
License-Expression: MIT
License-File: LICENSE
Classifier: Environment :: Console
Classifier: Intended Audience :: Developers
Classifier: License :: OSI Approved :: MIT License
Classifier: Natural Language :: English
Classifier: Operating System :: OS Independent
Classifier: Programming Language :: Python :: 3
Classifier: Programming Language :: Python :: 3.10
Classifier: Programming Language :: Python :: 3.11
Classifier: Topic :: Software Development
Classifier: Topic :: Software Development :: Libraries
Classifier: Topic :: Terminals
Classifier: Topic :: Text Processing
Classifier: Topic :: Utilities
Classifier: Typing :: Typed
Requires-Python: >=3.10
Requires-Dist: colorama<1,>=0.4.0
Requires-Dist: levenshtein<1,>=0.21.0
